Workbook

Sheet Read me
A1: OudhTrade — M01 Screen–Field Map
A2: One row per field on every screen: what the designer shows, what the frontend sends, where the backend stores it, and how QA checks it.
A4: Sheets | B4: Screens — one row per screen with counts, endpoints and components (from the Cross-Module Registers). Fields — one row per field. Open issues — mismatches found while mapping; each waits for a product-owner decision.
A5: Field ID | B5: Screen code + F + number, e.g. M01-S09-F01. Never reused or renumbered; a removed field is marked "Removed ({date})". ⚠ in the Field ID cell = the field has an open issue.
A6: Column colours | B6: Blue = designer (label, control, rules, visibility, error text) · Green = frontend (text key, API field, endpoint) · Brown = backend (table.column, type) · Grey = QA (requirement, test, source).
A7: Tab | B7: The tab of the screen the field sits on, from the register (sheet Tabs; Cross-Module Standards §4.2). "—" = the screen has no tabs; "A, B" = shown on both tabs; "Main tab (every settings screen)" = part of the common settings pattern; "Not stated — OI-nn" = the spec names no tab yet (open issue).
A8: Text key | B8: The name under which the label is stored in the translations table (M01-5 §4.1) in every language; the screen shows the text by this key. Pattern and parts (label, column, text, link, help, placeholder, error.<code>) in the Cross-Module Standards §8. Help, placeholder and error texts of a field use the same key with their own part.
A9: API field | B9: Proposed names made from the column names (camelCase). Final names are fixed by the backend lead in the API contract (OpenAPI).
A10: Table.column | B10: "setting <key>" = a value from the settings register (M01-2 §18); "— (derived: …)" = worked out, not stored.
A11: One source | B11: Exact texts and rules stay in the module documents (M01-6 UX, M01-5 database, M01-3 API). This map links them; when a document changes, the map is rebuilt.
A12: Changing a field | B12: Request through the question log → impact list (UX, database, API, requirement, test, register) → product-owner decision → one batch → rebuilt map and documents.
A13: Read-only | B13: Shared with the team as read-only. Only the "Product owner decision" column in Open issues is filled during review.
A16: Totals
A17: Screens | B17: =COUNTA(Screens!A2:A27) -> 26
A18: Fields | B18: =COUNTA(Fields!A2:A400) -> 399
A19: Open issues | B19: =COUNTIF('Open issues'!H2:H69,"Open") -> 0
A21: Built 29 Sep 2026 from the M01 documents and the Cross-Module Registers.

Sheet Screens
A1: Code | B1: Screen | C1: Menu label | D1: Kind | E1: Route | F1: UX section | G1: Tabs | H1: Fields | I1: Open issues | J1: Endpoints | K1: Components | L1: Tables | M1: Tests
A2: M01-AD-01 | B2: Settings editor | C2: Settings editor | D2: Admin | E2: /admin/settings | F2: M01-6 §12.2 | G2: Settings editor · History | H2: =COUNTIF(Fields!$B$2:$B$400,A2) -> 87 | I2: =COUNTIF('Open issues'!$C$2:$C$69,A2) -> 6 | J2: GET /v1/admin/settings PATCH /v1/admin/settings/{key} POST /v1/admin/settings/{key}/overrides DELETE …/overrides/{scope} settings-version API (M01-3 §4.2): /v1/admin/config/versions … | K2: SettingsTable, DraftEditor, ImpactPreview, ApprovalBar, PublishScheduler, VersionHistory & CompareView, OverridePanel | L2: config_versions, config_entries | M2: M01-TC-172, M01-TC-166, M01-TC-167, M01-TC-168, M01-TC-169, M01-TC-170, M01-TC-171, M01-TC-182, M01-TC-183, M01-TC-196, M01-TC-216
A3: M01-AD-02 | B3: Feature switches and overrides | C3: Feature switches | D3: Admin | E3: /admin/settings/switches | F3: M01-6 §12.3 | G3: Feature switches · History | H3: =COUNTIF(Fields!$B$2:$B$400,A3) -> 20 | I3: =COUNTIF('Open issues'!$C$2:$C$69,A3) -> 2 | J3: GET /v1/admin/switches PATCH /v1/admin/switches/{name} POST …/{name}/retire GET …/{name}/check?account= POST /v1/admin/config/emergency POST /v1/admin/maintenance/start · POST /v1/admin/maintenance/end POST /v1/admin/config/emergency/{versionId}/review (used on M16-AD-01) settings-version API (M01-3 §4.2): /v1/admin/config/versions … | K3: SettingsTable, DraftEditor, ImpactPreview, ApprovalBar, PublishScheduler, VersionHistory & CompareView, OverridePanel, EmergencyOffButton, MaintenancePanel | L3: feature_flags, config_versions, config_entries | M3: M01-TC-173, M01-TC-050, M01-TC-103, M01-TC-125, M01-TC-194, M01-TC-227, M01-TC-228, M01-TC-229, M01-TC-230, M01-TC-231, M01-TC-234
A4: M01-AD-03 | B4: Country table | C4: Country table | D4: Admin | E4: /admin/settings/countries · /admin/settings/countries/{code} | F4: M01-6 §12.4 | G4: List: Country table · Exchange rates · History Country detail: General · Status and features · Sign-in · ID rules ↗ · States and districts · History | H4: =COUNTIF(Fields!$B$2:$B$400,A4) -> 43 | I4: =COUNTIF('Open issues'!$C$2:$C$69,A4) -> 7 | J4: GET /v1/admin/countries GET /v1/admin/fx-rates PATCH /v1/admin/countries/{code} POST /v1/admin/countries/{code}/regions PATCH /v1/admin/regions/{code} POST /v1/admin/regions/{code}/districts PATCH /v1/admin/districts/{code} POST …/retire (regions, districts) settings-version API (M01-3 §4.2): /v1/admin/config/versions … | K4: SettingsTable, DraftEditor, ImpactPreview, ApprovalBar, PublishScheduler, VersionHistory & CompareView, FxRatesTab | L4: countries, country_regions, country_districts, fx_rates, config_versions | M4: M01-TC-174, M01-TC-119, M01-TC-162, M01-TC-198, M01-TC-208, M01-TC-217, M01-TC-238
A5: M01-AD-04 | B5: Reserved names | C5: Reserved names | D5: Admin | E5: /admin/settings/reserved-names | F5: M01-6 §12.5 | G5: Reserved names · History | H5: =COUNTIF(Fields!$B$2:$B$400,A5) -> 17 | I5: =COUNTIF('Open issues'!$C$2:$C$69,A5) -> 3 | J5: GET /v1/admin/reserved-names POST /v1/admin/reserved-names PATCH …/{id} POST …/{id}/retire GET …/matches?name= settings-version API (M01-3 §4.2): /v1/admin/config/versions … | K5: SettingsTable, DraftEditor, ImpactPreview, ApprovalBar, PublishScheduler, VersionHistory & CompareView | L5: reserved_names, url_slugs, config_versions | M5: M01-TC-175, M01-TC-143, M01-TC-202, M01-TC-203, M01-TC-218
A6: M01-AD-05 | B6: Holiday calendar | C6: Holiday calendar | D6: Admin | E6: /admin/settings/holidays | F6: M01-6 §12.6 | G6: Holiday calendar · History | H6: =COUNTIF(Fields!$B$2:$B$400,A6) -> 11 | I6: =COUNTIF('Open issues'!$C$2:$C$69,A6) -> 2 | J6: GET /v1/admin/holidays?country=&year= POST /v1/admin/holidays PATCH …/{id} POST …/{id}/retire POST /v1/admin/holidays/import settings-version API (M01-3 §4.2): /v1/admin/config/versions … | K6: SettingsTable, DraftEditor, ImpactPreview, ApprovalBar, PublishScheduler, VersionHistory & CompareView | L6: business_holidays, config_versions | M6: M01-TC-176, M01-TC-141, M01-TC-219
A7: M01-AD-06 | B7: Rate limits | C7: Rate limits | D7: Admin | E7: /admin/settings/rate-limits | F7: M01-6 §12.7 | G7: Rate limits · History | H7: =COUNTIF(Fields!$B$2:$B$400,A7) -> 10 | I7: =COUNTIF('Open issues'!$C$2:$C$69,A7) -> 6 | J7: GET /v1/admin/rate-limits PATCH /v1/admin/rate-limits/{module}/{group} POST …/overrides DELETE …/overrides/{scope} settings-version API (M01-3 §4.2): /v1/admin/config/versions … | K7: SettingsTable, DraftEditor, ImpactPreview, ApprovalBar, PublishScheduler, VersionHistory & CompareView, OverridePanel | L7: rate_limit_policies, rate_limit_blocks, config_versions | M7: M01-TC-177, M01-TC-197, M01-TC-220
A8: M01-AD-07 | B8: AI usage and budgets | C8: AI usage & budgets | D8: Admin | E8: /admin/settings/ai-usage | F8: M01-6 §12.8 | G8: AI usage & budgets · History | H8: =COUNTIF(Fields!$B$2:$B$400,A8) -> 13 | I8: =COUNTIF('Open issues'!$C$2:$C$69,A8) -> 3 | J8: GET /v1/admin/ai/usage?month= GET /v1/admin/ai/budgets PATCH /v1/admin/ai/budgets/{id} settings-version API (M01-3 §4.2): /v1/admin/config/versions … | K8: SettingsTable, DraftEditor, ImpactPreview, ApprovalBar, PublishScheduler, VersionHistory & CompareView | L8: ai_requests, ai_budgets, config_versions | M8: M01-TC-178, M01-TC-184, M01-TC-149, M01-TC-221
A9: M01-AD-08 | B9: Audit log viewer | C9: Audit log | D9: Admin | E9: /admin/audit · /admin/audit/{id} | F9: M01-6 §12.9 | G9: — | H9: =COUNTIF(Fields!$B$2:$B$400,A9) -> 15 | I9: =COUNTIF('Open issues'!$C$2:$C$69,A9) -> 1 | J9: GET /v1/admin/audit GET /v1/admin/audit/{id} POST /v1/admin/audit/export | K9: — (audit search and record pages; no named component in M01-4) | L9: audit_log, audit_verify_runs | M9: M01-TC-179, M01-TC-180, M01-TC-181, M01-TC-044, M01-TC-046, M01-TC-047, M01-TC-156
A10: M01-AD-09 | B10: Legal hold | C10: Legal holds | D10: Admin | E10: /admin/legal-holds · /admin/legal-holds/{id} | F10: M01-6 §12.10 | G10: Active · Released | H10: =COUNTIF(Fields!$B$2:$B$400,A10) -> 20 | I10: =COUNTIF('Open issues'!$C$2:$C$69,A10) -> 2 | J10: GET /v1/admin/legal-holds GET /v1/admin/legal-holds/{id} POST /v1/admin/legal-holds POST /v1/admin/legal-holds/{id}/release GET /v1/admin/legal-holds/coverage?scopeType=&scopeId= | K10: LegalHoldList & LegalHoldForm | L10: legal_holds, retention_policies | M10: M01-TC-185, M01-TC-186, M01-TC-055, M01-TC-222
A11: M01-AD-10 | B11: Failed jobs | C11: Failed jobs | D11: Admin | E11: /admin/jobs/failed | F11: M01-6 §12.11 | G11: Retrying · Dead-letter | H11: =COUNTIF(Fields!$B$2:$B$400,A11) -> 16 | I11: =COUNTIF('Open issues'!$C$2:$C$69,A11) -> 5 | J11: GET /v1/admin/jobs?status=retrying|dead&kind=&module=&from= POST /v1/admin/jobs/{id}/rerun POST /v1/admin/jobs/rerun POST /v1/admin/jobs/{id}/discard | K11: FailedJobsTable | L11: jobs | M11: M01-TC-187, M01-TC-052, M01-TC-053, M01-TC-223
A12: M01-AD-11 | B12: Retention policies | C12: Retention policies | D12: Admin | E12: /admin/settings/retention | F12: M01-6 §12.12 | G12: Retention policies · History | H12: =COUNTIF(Fields!$B$2:$B$400,A12) -> 11 | I12: =COUNTIF('Open issues'!$C$2:$C$69,A12) -> 4 | J12: GET /v1/admin/retention-policies PATCH /v1/admin/retention-policies/{dataType} settings-version API (M01-3 §4.2): /v1/admin/config/versions … | K12: RetentionPolicyTable, ImpactPreview, ApprovalBar, PublishScheduler, VersionHistory & CompareView | L12: retention_policies, retention_run_results, legal_holds, config_versions | M12: M01-TC-188, M01-TC-114, M01-TC-224
A13: M01-AD-12 | B13: Units and conversion factors | C13: Units & factors | D13: Admin | E13: /admin/settings/units · /admin/settings/units/land | F13: M01-6 §12.13 | G13: Units · Helper units · State land units · History | H13: =COUNTIF(Fields!$B$2:$B$400,A13) -> 28 | I13: =COUNTIF('Open issues'!$C$2:$C$69,A13) -> 4 | J13: GET /v1/admin/units POST /v1/admin/units PATCH …/{code} POST …/{code}/retire GET /v1/admin/units/land POST /v1/admin/units/land PATCH …/land/{unit}/{region} POST …/land/{unit}/{region}/retire GET /v1/admin/units/helper · PATCH /v1/admin/units/helper/{country} settings-version API (M01-3 §4.2): /v1/admin/config/versions … | K13: UnitTable & LandUnitTable, ImpactPreview, ApprovalBar, PublishScheduler, VersionHistory & CompareView | L13: units, area_unit_factors, config_versions | M13: M01-TC-189, M01-TC-190, M01-TC-226
... A27: M01-S11 | B27: Address form | C27: — | D27: User | E27: — (component in other modules’ forms, e.g. M02 sign-up, M03 business locations) | F27: M01-6 §7 | G27: — | H27: =COUNTIF(Fields!$B$2:$B$400,A27) -> 3 | I27: =COUNTIF('Open issues'!$C$2:$C$69,A27) -> 0 | J27: GET /v1/countries | K27: AddressForm | L27: countries, country_regions, country_districts | M27: M01-TC-074, M01-TC-099
A28: Total | H28: =SUM(H2:H27) -> 399 | I28: =SUM(I2:I27) -> 67

Sheet Fields
A1: Field ID | B1: Screen | C1: Area | D1: Tab | E1: Label | F1: Text key | G1: Control | H1: Required | I1: Values and limits | J1: Default | K1: Visibility | L1: Error text | M1: API field (proposed) | N1: Endpoint | O1: Table.column | P1: Type | Q1: Requirement | R1: Test | S1: Source
A2: M01-S01-F01 ⚠ OI-05 | B2: M01-S01 | C2: Standard mode | D2: — | E2: Add photos (up to 10) — Take photo · Choose from gallery (mobile) / Drop photos here or Browse (desktop) | F2: m01.s01.add_photos_take_photo.label | G2: File | H2: Yes (a listing has 1–10 photos) | I2: JPG, PNG, WEBP or iPhone photos (HEIC); max 15 MB each (setting files.photo.max_mb, 1–50 MB); up to 10 per listing (files.listing.photos_max, 1–30); type checked by file signature; decode limits 40 megapixels / 12,000 px a side (files.decode.*); size also enforced at storage (pre-signed POST content-length-range) | J2: — | K2: Signed-in user (own) | L2: “This file type isn’t supported” (FILE_TYPE_NOT_ALLOWED 415) · “Photo is larger than 15 MB” (FILE_TOO_LARGE 413) · “This photo is too large to process” · “We couldn’t use this file: our safety scan found a problem. Please upload a different file.” (FILE_INFECTED 422) · “Upload failed — Retry” · “You’ve added 10 photos, the maximum.” | M2: purpose · mimeType · sizeBytes | N2: POST /v1/files · POST /v1/files/{id}/complete | O2: files.mime_type / files.size_bytes (one row per photo; files.purpose e.g. listing_photo) | P2: text / bigint | Q2: M01-FR-FIL-001, M01-FR-FIL-002, M01-FR-FIL-005, M01-FR-FIL-018, M01-FR-FIL-025, M01-FR-SEC-011 | R2: M01-TC-001, M01-TC-002, M01-TC-003, M01-TC-006, M01-TC-018, M01-TC-082, M01-TC-145, M01-TC-155 | S2: M01-6 §3; M01-5 §2.1; M01-3 §2, §4, §4.3; M01-2 §3.1, §18
A3: M01-S01-F02 | B3: M01-S01 | C3: Standard mode | D3: — | E3: Upload progress “Uploading 60%” (Cancel ×) | F3: m01.s01.upload_progress.text | G3: Display | H3: — | I3: 0–100 % | J3: — | K3: Signed-in user (own) | L3: — | M3: uploadProgress | N3: — (browser → pre-signed S3 POST) | O3: — (derived: client upload progress; not stored) | P3: — | Q3: M01-FR-FIL-021 | R3: M01-TC-159 | S3: M01-6 §3; M01-4 §4
A4: M01-S01-F03 | B4: M01-S01 | C4: Standard mode | D4: — | E4: Status “Checking…” / Ready (safety scan and processing) | F4: m01.s01.status.text | G4: Display | H4: — | I4: files.status: pending_upload, uploaded, scanning, processing, held, in_review, ready, attached, expired, rejected_infected, rejected, failed, deleted (“Checking…” = scanning / processing) | J4: — | K4: Signed-in user (own) | L4: — | M4: status | N4: GET /v1/files/{id} | O4: files.status | P4: text | Q4: M01-FR-FIL-018 | R4: M01-TC-018 | S4: M01-6 §3; M01-5 §2.1; M01-3 §2.1
A5: M01-S01-F04 | B5: M01-S01 | C5: Standard mode | D5: — | E5: Thumbnail | F5: m01.s01.thumbnail.text | G5: Display | H5: — | I5: variants thumb 320, medium 800, large 1600 (WEBP + JPG); location and EXIF removed from all variants; faces blurred for farm-visit and business-location photos (variant blurred) | J5: — | K5: Signed-in user (own) | L5: — | M5: variants[] (variant · storageKey) | N5: GET /v1/files/{id} | O5: file_variants.variant / file_variants.storage_key | P5: text / text | Q5: M01-FR-FIL-003, M01-FR-FIL-004, M01-FR-FIL-028 | R5: M01-TC-004, M01-TC-005, M01-TC-193, M01-TC-199 | S5: M01-6 §3; M01-5 §2.2; M01-3 §2
A6: M01-S01-F05 ⚠ OI-01 | B6: M01-S01 | C6: Standard mode | D6: — | E6: “Cover” tag on the first photo; drag handle to reorder (button alternatives “Move left”, “Move right”, “Make cover”) | F6: m01.s01.cover.text | G6: Display | H6: — | I6: first photo is the cover; order changed by drag or buttons | J6: — | K6: Signed-in user (own) | L6: — | M6: position (M05 listing-photo link) | N6: — | O6: M05 listing-photo link, position column (photo order and cover are stored by M05, M01-5 §2.1) | P6: — | Q6: M01-FR-FIL-005 | R6: M01-TC-007, M01-TC-158 | S6: M01-6 §3, §11; M01-2 FIL-005; M01-5 §2.1
A7: M01-S01-F06 | B7: M01-S01 | C7: Standard mode | D7: — | E7: Counter “4 of {n}” | F7: m01.s01.counter.text | G7: Display | H7: — | I7: count of photos ÷ setting files.listing.photos_max (default 10, 1–30) | J7: — | K7: Signed-in user (own) | L7: “You’ve added {n} photos, the maximum.” (Add button disabled) | M7: photoCount (proposal) | N7: — | O7: — (derived: photos in the form ÷ setting files.listing.photos_max) | P7: — | Q7: M01-FR-FIL-005 | R7: M01-TC-006 | S7: M01-6 §3; M01-2 §18
A8: M01-S01-F07 | B8: M01-S01 | C8: Standard mode | D8: — | E8: Quality warning — amber badge “This photo is small or blurry — buyers prefer clear photos.” | F8: m01.s01.quality_warning_amber_badge.text | G8: Display | H8: — | I8: small (short side below 800 px, setting files.photo.quality_min_px 320–2,000) or blurred; warns only — photo still accepted | J8: — | K8: Signed-in user (own) | L8: — | M8: qualityWarning | N8: GET /v1/files/{id} | O8: files.quality_warning | P8: text (small, blurred or null) | Q8: M01-FR-FIL-006 | R8: M01-TC-008 | S8: M01-6 §3; M01-5 §2.1; M01-2 §18
A9: M01-S01-F08 ⚠ OI-04 | B9: M01-S01 | C9: Standard mode | D9: — | E9: Held for review — amber chip “Held — this photo seems to show contact details (a phone number, email, web address, payment ID or QR code). Contact details aren’t allowed in photos. Our team will check it.” (Replace photo) | F9: m01.s01.held_review_amber_chip.text | G9: Display | H9: — | I9: status held; safety_flags found text types: phone, email, upi, url, qr | J9: — | K9: Signed-in user (own) | L9: — | M9: status · safetyFlags | N9: GET /v1/files/{id} | O9: files.status (held) + files.safety_flags | P9: text / jsonb | Q9: M01-FR-FIL-023 | R9: M01-TC-078, M01-TC-079 | S9: M01-6 §3; M01-5 §2.1; M01-3 §2
A10: M01-S01-F09 | B10: M01-S01 | C10: Standard mode | D10: — | E10: Copied photo — “This photo matches another seller’s photo. Please use your own photos.” | F10: m01.s01.copied_photo.text | G10: Display | H10: — | I10: while suspected: status stays ready / attached and nothing is shown to the seller; message only after moderation (M12) confirms | J10: — | K10: Signed-in user (own) | L10: — | M10: duplicateSuspected · status · rejectReason | N10: GET /v1/files/{id} | O10: files.duplicate_suspected → files.status (rejected) + files.reject_reason after moderation.file_decided | P10: boolean / text / text | Q10: M01-FR-FIL-024, M01-FR-FIL-025 | R10: M01-TC-080, M01-TC-081, M01-TC-200 | S10: M01-6 §3; M01-5 §2.1; M01-3 §2, §5.1
A11: M01-S01-F10 | B11: M01-S01 | C11: Standard mode | D11: — | E11: Rejection / failure reason (e.g. image_too_large → “This photo is too large to process”) | F11: m01.s01.rejection_failure_reason.text | G11: Display | H11: — | I11: set for rejected or failed files | J11: — | K11: Signed-in user (own) | L11: “This photo is too large to process” | M11: rejectReason | N11: GET /v1/files/{id} | O11: files.reject_reason | P11: text | Q11: M01-FR-FIL-018, M01-FR-FIL-001 | R11: M01-TC-155 | S11: M01-6 §3; M01-5 §2.1; M01-3 §2
A12: M01-S01-F11 | B12: M01-S01 | C12: Standard mode | D12: — | E12: Location note “Location is never shown publicly. OudhTrade staff may use it to check origin.” | F12: m01.s01.location_note.text | G12: Display | H12: — | I12: shown only for purposes that keep the location: farm_visit_photo, verification_photo, verification_doc, location_photo, origin_photo, origin_doc; for all other purposes location is removed at upload and no note is shown | J12: — | K12: Signed-in user (own) — note only; the location itself is Private (photo_location.view) | L12: — | M12: purpose | N12: POST /v1/files | O12: files.purpose (decides); files.location_private is never returned to the uploader | P12: text / bytea (encrypted) | Q12: M01-FR-FIL-022 | R12: M01-TC-195 | S12: M01-6 §3; M01-5 §2.1; M01-2 FIL-022
... A400: M01-AD-12-F28 | B400: M01-AD-12 | C400: Units tab — Add unit | D400: Units | E400: Add unit — Helper only | F400: m01.ad12.units.add_unit_helper_only.label | G400: Switch | H400: Yes | I400: yes / no | J400: — | K400: Staff — view: Super Admin, Admin, Moderator, Finance, Content Editor, Support; edit: Super Admin, Admin | L400: — | M400: is_helper_only | N400: POST /v1/admin/units (draftId) | O400: units.is_helper_only | P400: boolean | Q400: M01-FR-UNT-001 | R400: M01-TC-226 | S400: M01-6 §12.13; M01-5 §3.1

Sheet Open issues
A1: ID | B1: Field | C1: Screen | D1: Kind | E1: Problem | F1: Suggestion | G1: Product owner decision | H1: Status
A2: OI-01 | B2: M01-S01-F05 | C2: M01-S01 | D2: No column | E2: Photo order and the cover (first photo) have no column: files has no position / order column and no M01 table records the order, yet FIL-005 requires reordering by drag and the first photo is the cover. | F2: State in M01-5 (or the M05 design) where the order is stored, e.g. a position column on the listing-photo link owned by M05, and cite it here. | G2: Photo order and cover are stored by M05 on its listing-photo link (position column); M01-5 says so. | H2: Decided (29 Sep 2026)
A3: OI-02 | B3: M01-S01-F12 | C3: M01-S01 | D3: Other | E3: The watermark toggle writes files.has_watermark, but no endpoint carries it: POST /v1/files / FileService.createUploadSlot(owner, purpose, type, size) has no watermark parameter. The label “to my photos” also suggests an account-level choice, while the column is per file. | F3: Add hasWatermark to POST /v1/files (or a PATCH on the file) and say whether the choice is per file or remembered per account. | G3: Remember per account: user_preferences.watermark_default; each photo keeps files.has_watermark. | H3: Decided (29 Sep 2026)
A4: OI-03 | B4: M01-S03-F01 | C4: M01-S03 | D4: No screen | E4: files.side (front, back, selfie or page for ID and document scans) is set by no screen and no API parameter: the document uploader has no side selector and POST /v1/files takes only owner, purpose, type and size. | F4: Add a side parameter to POST /v1/files (set by the M03 / M06 form) or drop the column. | G4: Add side to POST /v1/files; the M03 / M06 form shows one slot per side. | H4: Decided (29 Sep 2026)
A5: OI-04 | B5: M01-S01-F08 | C5: M01-S01 | D5: Label mismatch | E5: The held-photo chip names only “a phone number, payment ID or QR code”, but the check also holds for email addresses and web addresses (files.safety_flags: phone, email, upi, url, qr; FIL-023). | F5: Show the found type from safety_flags, or add email and web address to the text. | G5: Use M01-6 wording; the chip names all found types (phone number, email, web address, payment ID or QR code). | H5: Decided (29 Sep 2026)
A6: OI-05 | B6: M01-S01-F01 | C6: M01-S01 | D6: Limit mismatch | E6: The uploader texts fix the limits: “Add photos (up to 10) … max 15 MB”, “Photo is larger than 15 MB”, “You’ve added 10 photos, the maximum.”, “4 of 10”; video “up to 60 seconds … max 100 MB”; documents “max 10 MB”. These are settings with ranges (files.photo.max_mb 1–50, files.listing.photos_max 1–30, files.video.* , files.document.max_mb 1–25) and can be overridden by plan or category (TC-076 expects 15 photos); M01-3 §4.3 already uses {max}. | F6: Write the texts with placeholders filled from the settings ({max} MB, {n} photos, {seconds}). | G6: Texts use placeholders from the settings ({n}, {max}, {seconds}). | H6: Decided (29 Sep 2026)
A7: OI-06 | B7: M01-S02-F03 | C7: M01-S02 | D7: Other | E7: The uploaders are also used for business-location media (FIL-026: up to 2 photos per location, video ≤ 45 s and ≤ 45 MB, server compresses), but M01-6 §3 / §4 give only the listing limits and texts (10 photos, 60 s, 100 MB). M01-4 §4 mentions 45 s / 45 MB. | F7: Add the business-location states and texts (limits from files.location_photo.max_per_location and files.location_video.*) to M01-6 §3 and §4. | G7: Business-location limits and texts added to M01-6 §3 and §4. | H7: Decided (29 Sep 2026)
A8: OI-07 | B8: M01-S02-F03 | C8: M01-S02 | D8: Label mismatch | E8: The too-long video message differs: M01-2 FIL-012 requires “Video must be 60 seconds or shorter”, while M01-6 §4 and M01-3 VIDEO_TOO_LONG say “This video is {length}. Please trim it to {max} seconds or less.” | F8: Align FIL-012 with the M01-6 / M01-3 wording. | G8: FIL-012 uses the M01-6 / M01-3 wording. | H8: Decided (29 Sep 2026)
A9: OI-08 | B9: M01-S02-F03 | C9: M01-S02 | D9: No test | E9: No error text for a video larger than 100 MB in M01-6 §4 (only the generic FILE_TOO_LARGE “File is larger than {max} MB.” in M01-3), and no test for the size limit: TC-013 uploads 90 MB; the test sample set lists a 120 MB video but no test case uses it. | F9: Add the oversize state to M01-6 §4 and a test (e.g. upload a 120 MB video → refused). | G9: Oversize state added to M01-6 §4; test M01-TC-209. | H9: Decided (29 Sep 2026)
A10: OI-09 | B10: M01-S02-F02 | C10: M01-S02 | D10: Other | E10: “Video: 1 of 2 used on your plan.” needs the used and total allowance, but no M01-3 endpoint returns it; the allowance is only enforced as 403 UPLOAD_ALLOWANCE_USED on POST /v1/files. | F10: Name the read endpoint (e.g. GET /v1/me/allowances from M11, or a field on GET /v1/files). | G10: GET /v1/me/allowances (Module 11 plan allowance). | H10: Decided (29 Sep 2026)
A11: OI-10 | B11: M01-S05-F03 | C11: M01-S05 | D11: No test | E11: No test sets the Choose panel toggles separately (e.g. Analytics on, Marketing off → Save choices), and none checks that the choice is asked again after 12 months (CKE-005; setting cookies.consent_months 6–12). TC-058 / TC-059 cover Reject all and Accept only. | F11: Add tests for mixed toggles and for the 12-month re-ask. | G11: Tests M01-TC-210 (toggles) and M01-TC-211 (asked again). | H11: Decided (29 Sep 2026)
A12: OI-11 | B12: M01-S06-F04 | C12: M01-S06 | D12: No column | E12: The sign-in row shows a place (“Guwahati, IN”), but audit_log stores only ip (inet); no column, lookup or rule says how the place is found. | F12: Specify the IP-to-place lookup (and that the place is not stored), or store a coarse place when the sign-in is recorded. | G12: Store city and country (audit_log.geo_city / geo_country) when the sign-in is recorded. | H12: Decided (29 Sep 2026)
... A69: OI-68 | B69: — | C69: — | D69: Other | E69: M01-6 §7 specifies a phone field (flag and country-code picker) and an address form (fields by country), and M01-4 builds PhoneInput and AddressForm, but they have no screen code in the register, so their fields are not in this map. | F69: Give them component codes (e.g. M01-S10, M01-S11) or state which module screens own them. | G69: New codes M01-S10 Phone number field and M01-S11 Address form. | H69: Decided (29 Sep 2026)
